{
    "WEBPAGES":
    {
        "kopernik":
        {
            "URL":"https://www.kopernikus.pl",
            "CHECK_ELEMENTS":
            {
                "poland_emblem_test":
                {
                    "ELEMENT_TYPE":"div",
                    "ELEMENT_TAG_TYPE":"class",
                    "ELEMENT_TAG_VALUE":"poland-emblem"

                }
            }
        },


        "interia":
        {
            "URL":"https://www.interia.pl",
            "CHECK_ELEMENTS":
            {
                "x":
                {
                    "ELEMENT_TYPE":"d",
                    "ELEMENT_TAG_TYPE":"as",
                    "ELEMENT_TAG_VALUE":"lgg"
                }
            }
        },



        "webpage_alias":
        {
            "URL":"site_url",
            "CHECK_ELEMENTS":
            {
                "element_alias":
                {
                    "ELEMENT_TYPE":"like: a or div or h1",
                    "ELEMENT_TAG_TYPE":"like: class",
                    "ELEMENT_TAG_VALUE":"like: class value"
                }
            }
        }



    }

}